auto_jift/__init__.py
auto_jift-0.0.4.dist-info/METADATA
auto_jift-0.0.4.dist-info/WHEEL
auto_jift-0.0.4.dist-info/top_level.txt
auto_jift-0.0.4.dist-info/RECORD
