Metadata-Version: 2.1
Name: auto-jift
Version: 0.0.4
Summary: Jiangxi Institute Of Fashion Technology automated office
Home-page: UNKNOWN
Author: chenzhenhua
Author-email: yinluofeihua@163.com
License: UNKNOWN
Platform: UNKNOWN
Requires-Python: >=3.6
Requires-Dist: openpyxl (==3.0.7)
Requires-Dist: xltpl (==0.9.2)
Requires-Dist: xlwt (==1.3.0)
Requires-Dist: numpy (==1.19.4)
Requires-Dist: chinese-calendar (==1.5.0)
Requires-Dist: pandas (==1.1.5)
Requires-Dist: xlrd (==1.2.0)
